braintools/__init__.py
braintools/_misc.py
braintools/_spike_encoder.py
braintools/_spike_encoder_test.py
braintools/_spike_operation.py
braintools/_spike_operation_test.py
braintools/tree.py
braintools/tree_test.py
braintools/conn/__init__.py
braintools/conn/_base.py
braintools/conn/_base_test.py
braintools/conn/_biological.py
braintools/conn/_biological_test.py
braintools/conn/_compartment.py
braintools/conn/_compartment_test.py
braintools/conn/_kernel.py
braintools/conn/_kernel_test.py
braintools/conn/_random.py
braintools/conn/_random_test.py
braintools/conn/_regular.py
braintools/conn/_regular_test.py
braintools/conn/_spatial.py
braintools/conn/_spatial_test.py
braintools/conn/_topological.py
braintools/conn/_topological_test.py
braintools/file/__init__.py
braintools/file/_matfile.py
braintools/file/_matfile_test.py
braintools/file/_msg_checkpoint.py
braintools/file/_msg_checkpoint_test.py
braintools/init/__init__.py
braintools/init/_distance_base.py
braintools/init/_distance_base_test.py
braintools/init/_distance_impl.py
braintools/init/_distance_impl_test.py
braintools/init/_init_base.py
braintools/init/_init_base_test.py
braintools/init/_init_basic.py
braintools/init/_init_basic_test.py
braintools/init/_init_composite.py
braintools/init/_init_composite_test.py
braintools/init/_init_orthogonal.py
braintools/init/_init_orthogonal_test.py
braintools/init/_init_variance_scaling.py
braintools/init/_init_variance_scaling_test.py
braintools/init/_init_with_distance.py
braintools/init/_init_with_distance_test.py
braintools/input/__init__.py
braintools/input/_composable_base.py
braintools/input/_composable_base_test.py
braintools/input/_composable_basic.py
braintools/input/_composable_basic_test.py
braintools/input/_composable_pulses.py
braintools/input/_composable_pulses_test.py
braintools/input/_composable_stochastic.py
braintools/input/_composable_stochastic_test.py
braintools/input/_composable_waveforms.py
braintools/input/_composable_waveforms_test.py
braintools-0.1.7.dist-info/licenses/LICENSE
braintools-0.1.7.dist-info/METADATA
braintools-0.1.7.dist-info/WHEEL
braintools-0.1.7.dist-info/top_level.txt
braintools-0.1.7.dist-info/RECORD
