Metadata-Version: 2.4
Name: braintools
Version: 0.1.7
Summary: Modeling tools for brain simulation.
Author-email: BrainTools Developers <chao.brain@qq.com>
License: 
Project-URL: homepage, https://github.com/chaobrain/braintools
Project-URL: repository, https://github.com/chaobrain/braintools
Project-URL: Bug Tracker, https://github.com/chaobrain/braintools/issues
Project-URL: Documentation, https://braintools.readthedocs.io/
Keywords: brain dynamics programming,brain simulation,brain-inspired computing,brain-inspired computation,brain modeling,brain modeling toolbox
Classifier: Development Status :: 4 - Beta
Classifier: Intended Audience :: Developers
Classifier: Intended Audience :: Science/Research
Classifier: Natural Language :: English
Classifier: Operating System :: OS Independent
Classifier: Programming Language :: Python
Classifier: Programming Language :: Python :: 3
Classifier: Programming Language :: Python :: 3.10
Classifier: Programming Language :: Python :: 3.11
Classifier: Programming Language :: Python :: 3.12
Classifier: Programming Language :: Python :: 3.13
Classifier: Programming Language :: Python :: 3.14
Classifier: Topic :: Scientific/Engineering :: Artificial Intelligence
Classifier: Topic :: Scientific/Engineering :: Bio-Informatics
Classifier: Topic :: Scientific/Engineering :: Mathematics
Classifier: Topic :: Software Development :: Libraries
Requires-Python: >=3.10
License-File: LICENSE
Requires-Dist: jax
Requires-Dist: numpy>=1.15
Requires-Dist: brainstate>=0.1.0
Requires-Dist: brainunit>=0.0.8
Requires-Dist: typing_extensions
Requires-Dist: optax
Requires-Dist: matplotlib
Requires-Dist: msgpack
Requires-Dist: scipy
Provides-Extra: testing
Requires-Dist: jax; extra == "testing"
Requires-Dist: brainstate; extra == "testing"
Requires-Dist: brainunit; extra == "testing"
Requires-Dist: matplotlib; extra == "testing"
Requires-Dist: nevergrad; extra == "testing"
Requires-Dist: scipy; extra == "testing"
Requires-Dist: msgpack; extra == "testing"
Requires-Dist: optax; extra == "testing"
Requires-Dist: pytest; extra == "testing"
Requires-Dist: absl-py; extra == "testing"
Requires-Dist: typing_extensions; extra == "testing"
Provides-Extra: cpu
Requires-Dist: jax[cpu]; extra == "cpu"
Requires-Dist: brainstate; extra == "cpu"
Requires-Dist: brainunit; extra == "cpu"
Requires-Dist: matplotlib; extra == "cpu"
Requires-Dist: scipy; extra == "cpu"
Requires-Dist: msgpack; extra == "cpu"
Requires-Dist: optax; extra == "cpu"
Requires-Dist: typing_extensions; extra == "cpu"
Provides-Extra: cuda12
Requires-Dist: jax[cuda12]; extra == "cuda12"
Requires-Dist: brainstate; extra == "cuda12"
Requires-Dist: brainunit; extra == "cuda12"
Requires-Dist: matplotlib; extra == "cuda12"
Requires-Dist: scipy; extra == "cuda12"
Requires-Dist: msgpack; extra == "cuda12"
Requires-Dist: optax; extra == "cuda12"
Requires-Dist: typing_extensions; extra == "cuda12"
Provides-Extra: cuda13
Requires-Dist: jax[cuda13]; extra == "cuda13"
Requires-Dist: brainstate; extra == "cuda13"
Requires-Dist: brainunit; extra == "cuda13"
Requires-Dist: matplotlib; extra == "cuda13"
Requires-Dist: scipy; extra == "cuda13"
Requires-Dist: msgpack; extra == "cuda13"
Requires-Dist: optax; extra == "cuda13"
Requires-Dist: typing_extensions; extra == "cuda13"
Provides-Extra: tpu
Requires-Dist: jax[tpu]; extra == "tpu"
Requires-Dist: brainstate; extra == "tpu"
Requires-Dist: brainunit; extra == "tpu"
Requires-Dist: matplotlib; extra == "tpu"
Requires-Dist: scipy; extra == "tpu"
Requires-Dist: msgpack; extra == "tpu"
Requires-Dist: optax; extra == "tpu"
Requires-Dist: typing_extensions; extra == "tpu"
Dynamic: license-file
